[1,["c0UWuza6RIGqZtUAWM4Erx","87OdMeAhJEEav+e3J2mIDM","f2ffUSkJRObr186gXEwFbi","caEG6VXp1PAb7RpguMlrYt"],["_textureSetter"],["cc.SpriteFrame"],0,[[[{"name":"si","rect":[0,0,73,73],"offset":[0,0],"originalSize":[73,73],"capInsets":[18,13,15,13]}],[0],0,[0],[0],[0]],[[{"name":"oi","rect":[0,0,508,231],"offset":[0,0],"originalSize":[508,231],"capInsets":[0,0,0,0]}],[0],0,[0],[0],[1]],[[{"name":"sd","rect":[0,0,656,58],"offset":[0,0],"originalSize":[656,58],"capInsets":[0,0,0,0]}],[0],0,[0],[0],[2]],[[{"name":"mq","rect":[0,0,91,91],"offset":[0,0],"originalSize":[91,91],"capInsets":[0,0,0,0]}],[0],0,[0],[0],[3]]]]